[
    {
        "id": 1,
        "name": "Mario",
        "image": "https://www5.minijuegosgratis.com/v3/games/thumbnails/222662_1.jpg",
        "occupation": "Plumber",
        "location": "1-1"
    },
    {
        "id": 2,
        "name": "Lara Croft",
        "image": "https://upload.wikimedia.org/wikipedia/en/7/7a/Lara_Croft.png",
        "occupation": "Cave Explorer",
        "location": "An Ominous Cave"
    },
    {
        "id": 3,
        "name": "Bowser",
        "image": "https://www.mariowiki.com/images/thumb/e/e9/Tanooki_Bowser.png/1200px-Tanooki_Bowser.png",
        "occupation": "Bad Guy",
        "location": "8-4"
    },
    {
        "id": 4,
        "name": "Sonic",
        "image": "https://vignette.wikia.nocookie.net/great-characters/images/2/2d/TSR_Sonic.png/revision/latest?cb=20190508153540",
        "occupation": "Ring Gatherer",
        "location": "Emerald Hill"
    },
    {
        "id": 5,
        "name": "Rennyn",
        "image": "https://i.pinimg.com/originals/d9/29/79/d929790e228555be995b9458534f83a7.jpg",
        "occupation": "Rogue",
        "location": "Vixon Tor"
    },
    {
        "id": 6,
        "name": "Link",
        "image": "https://vignette.wikia.nocookie.net/character-stats-and-profiles/images/d/d6/Adult_Link.png/revision/latest?cb=20170430215801",
        "occupation": "Adventurer",
        "location": "Hyrule"
    },
    {
        "id": 7,
        "name": "Crono",
        "image": "https://vignette.wikia.nocookie.net/characterprofile/images/6/67/Chrono_Trigger_-_Crono_as_he_first_appeared_for_Super_Nintendo.png/revision/latest?cb=20160805045521",
        "occupation": "Time Explorer",
        "location": "The Millennial Fair"
    },
    {
        "id": 8,
        "name": "Toejam",
        "image": "https://statici.behindthevoiceactors.com/behindthevoiceactors/_img/chars/toejam-toejam-earl-back-in-the-groove-2.49.jpg",
        "occupation": "Intergalactic DJ",
        "location": "Earth"
    },
    {
        "id": 9,
        "name": "Ecco",
        "image": "https://www.borisjulie.com/wp-content/uploads/2018/07/B-910.jpg",
        "occupation": "Dolphin",
        "location": "The Ocean"
    },
    {
        "id": 10,
        "name": "Jason",
        "image": "https://vignette.wikia.nocookie.net/23a71762-b93f-473b-8249-e0a68056aeb9/scale-to-width-down/800",
        "occupation": "Camp Terror",
        "location": "Crystal Lake"
    },
    {
        "id": 11,
        "name": "Axel",
        "image": "https://vignette.wikia.nocookie.net/projectxzone/images/6/60/PXZ2-Axel_Stone.png/revision/latest?cb=20170608044026",
        "occupation": "Martial Artist",
        "location": "The Streets"
    },
    {
        "id": 12,
        "name": "Giygas",
        "image": "https://i.ytimg.com/vi/7E2kHsamg44/maxresdefault.jpg",
        "occupation": "Galaxy Devourer",
        "location": "Earth's Core"
    }
]